{
    "type":"FeatureCollection",
    "metadata":{
      "name":"Зона доставки",
      "creator":"Yandex Map Constructor",
      "description":"На данный момент мы доставляем в пределах желтой и синей границ"
    },
    "features":[
      {
        "type":"Feature",
        "id":0,
        "geometry":{
          "type":"Polygon",
          "coordinates":[
            [
              [
                104.2812635272918,
                52.26171158449481
              ],
              [
                104.28356519180292,
                52.26067225516424
              ],
              [
                104.28773714770827,
                52.259371067836994
              ],
              [
                104.29252371980843,
                52.259491566726524
              ],
              [
                104.29888524277618,
                52.25815790045579
              ],
              [
                104.30847830656035,
                52.25556063758044
              ],
              [
                104.31651949317501,
                52.2523570289957
              ],
              [
                104.32496837555982,
                52.24991705251826
              ],
              [
                104.3309539295229,
                52.24892185140377
              ],
              [
                104.3358236845358,
                52.24919098351705
              ],
              [
                104.34101416807238,
                52.25115158231291
              ],
              [
                104.3437294562534,
                52.249554346186734
              ],
              [
                104.34485687669765,
                52.248167780577226
              ],
              [
                104.34505178106262,
                52.246342843232135
              ],
              [
                104.34588278652707,
                52.24480560514018
              ],
              [
                104.34816411912072,
                52.24360818788533
              ],
              [
                104.35301355301964,
                52.244569722356395
              ],
              [
                104.35844234406581,
                52.245149267265504
              ],
              [
                104.3600302118026,
                52.24609759706977
              ],
              [
                104.36234764039146,
                52.24570246212695
              ],
              [
                104.36530879914392,
                52.24630833425986
              ],
              [
                104.36711124360197,
                52.24860003624705
              ],
              [
                104.37650970399017,
                52.246703463780094
              ],
              [
                104.38044615174346,
                52.24819601019439
              ],
              [
                104.3836959539889,
                52.25082111457811
              ],
              [
                104.38533850098658,
                52.25289762106479
              ],
              [
                104.38612274109953,
                52.25494769293895
              ],
              [
                104.35337833344579,
                52.26118910407898
              ],
              [
                104.34788044408832,
                52.26529336938268
              ],
              [
                104.34698394715426,
                52.26633036293136
              ],
              [
                104.34669426858062,
                52.26706430940131
              ],
              [
                104.3468122857773,
                52.26771267347905
              ],
              [
                104.3490331548416,
                52.26911468707277
              ],
              [
                104.34947035491099,
                52.26939442623613
              ],
              [
                104.34977880894773,
                52.26968732769484
              ],
              [
                104.3501489537918,
                52.270312616435305
              ],
              [
                104.35031793295971,
                52.27145621369982
              ],
              [
                104.35044399678347,
                52.27304732776158
              ],
              [
                104.35124329506985,
                52.27321844726117
              ],
              [
                104.35236445843809,
                52.27332375123911
              ],
              [
                104.35442439496154,
                52.27340931053624
              ],
              [
                104.35517541348575,
                52.2738502673568
              ],
              [
                104.35548386752245,
                52.27397202331377
              ],
              [
                104.35665062844397,
                52.274027965127736
              ],
              [
                104.35613564431308,
                52.279276307879805
              ],
              [
                104.3572943586075,
                52.279414500314374
              ],
              [
                104.35721389233706,
                52.28056937729784
              ],
              [
                104.35691884934545,
                52.281224123177566
              ],
              [
                104.35758403718118,
                52.28238224283415
              ],
              [
                104.3576108592713,
                52.28439571935907
              ],
              [
                104.35750893532875,
                52.286409103930936
              ],
              [
                104.35733920533693,
                52.287055765249946
              ],
              [
                104.35692857235311,
                52.28789050311774
              ],
              [
                104.35494273185374,
                52.28781915859359
              ],
              [
                104.35268766462447,
                52.288123862642394
              ],
              [
                104.34967956721427,
                52.288864848044895
              ],
              [
                104.34683910786754,
                52.28847832003281
              ],
              [
                104.34459141671306,
                52.28807369558907
              ],
              [
                104.34241346299297,
                52.28715916486967
              ],
              [
                104.34024623810892,
                52.286803874437275
              ],
              [
                104.33767131745458,
                52.288093433453525
              ],
              [
                104.33539680420985,
                52.28810659202437
              ],
              [
                104.33301500260461,
                52.287678936455
              ],
              [
                104.33107308327777,
                52.28709666027894
              ],
              [
                104.32909361302481,
                52.287476621028425
              ],
              [
                104.32763180911168,
                52.28741658415815
              ],
              [
                104.32587093889342,
                52.286794416434894
              ],
              [
                104.32381033181773,
                52.28577273465718
              ],
              [
                104.32168568700179,
                52.28584089548876
              ],
              [
                104.32004400744661,
                52.28616447808946
              ],
              [
                104.31834340311217,
                52.28633942759728
              ],
              [
                104.3172356088795,
                52.28641374301875
              ],
              [
                104.3158703225814,
                52.286974940558665
              ],
              [
                104.31474082833887,
                52.287759675940706
              ],
              [
                104.31425506425991,
                52.28893914873763
              ],
              [
                104.3139025924474,
                52.28979395217563
              ],
              [
                104.3117047608328,
                52.290780316943
              ],
              [
                104.31014466987808,
                52.291373601712905
              ],
              [
                104.30957163184078,
                52.29189387985435
              ],
              [
                104.30895567845923,
                52.2923088934639
              ],
              [
                104.30640603424452,
                52.293436620628924
              ],
              [
                104.3037529204366,
                52.294496582485834
              ],
              [
                104.30153659760592,
                52.29520067308848
              ],
              [
                104.29760575517777,
                52.29597161975357
              ],
              [
                104.2948336270441,
                52.29721616606262
              ],
              [
                104.29234453707842,
                52.298926393323306
              ],
              [
                104.2869372037044,
                52.29455860431649
              ],
              [
                104.27998415842451,
                52.29295044943755
              ],
              [
                104.27620722837494,
                52.29180425722366
              ],
              [
                104.27105700730979,
                52.29128960543344
              ],
              [
                104.26698782818845,
                52.289106979883506
              ],
              [
                104.26589393389197,
                52.28719821941447
              ],
              [
                104.266516653365,
                52.285026187306045
              ],
              [
                104.27015554616561,
                52.282615467596834
              ],
              [
                104.272614266999,
                52.280112489479045
              ],
              [
                104.2748801065933,
                52.27895266504153
              ],
              [
                104.27561605945611,
                52.27724742094875
              ],
              [
                104.27568362847794,
                52.27583538286637
              ],
              [
                104.27431353346783,
                52.27456808851974
              ],
              [
                104.27392675633553,
                52.27310043307234
              ],
              [
                104.27321849374577,
                52.27184432919076
              ],
              [
                104.27414101423717,
                52.27058818953614
              ],
              [
                104.2758191496616,
                52.26947854915531
              ],
              [
                104.27586650200503,
                52.26684177703718
              ],
              [
                104.27793531252688,
                52.265622852475815
              ],
              [
                104.27975594552593,
                52.262589786268954
              ],
              [
                104.2812635272918,
                52.26171158449481
              ]
            ]
          ]
        },
        "properties":{
          "description":"Сумма заказа от 800 руб.",
          "fill":"#ffd21e",
          "fill-opacity":0.6,
          "stroke":"#ffd21e",
          "stroke-width":"5",
          "stroke-opacity":0.9
        }
      },
      {
        "type":"Feature",
        "id":1,
        "geometry":{
          "type":"Polygon",
          "coordinates":[
            [
              [
                104.29892030765488,
                52.3130528650576
              ],
              [
                104.2986120493431,
                52.31321778322624
              ],
              [
                104.29819506370374,
                52.31323941844302
              ],
              [
                104.29772443388407,
                52.31320844938297
              ],
              [
                104.29646667358102,
                52.31309061901592
              ],
              [
                104.29459584522996,
                52.31292918983794
              ],
              [
                104.29368457093555,
                52.3128698456926
              ],
              [
                104.29273038129693,
                52.312849955030785
              ],
              [
                104.29075054925465,
                52.31284625848239
              ],
              [
                104.29002885413499,
                52.31282139563102
              ],
              [
                104.28931788785138,
                52.31275379135304
              ],
              [
                104.29003385442684,
                52.310891970025466
              ],
              [
                104.29107814345076,
                52.308820518119404
              ],
              [
                104.2923875725041,
                52.306574691154665
              ],
              [
                104.29342465979659,
                52.30358555789696
              ],
              [
                104.29328239462289,
                52.29977879476555
              ],
              [
                104.2977455904237,
                52.29631887170736
              ],
              [
                104.30238044760142,
                52.295371621068895
              ],
              [
                104.30542743704234,
                52.29429278304208
              ],
              [
                104.30881774923716,
                52.29279289117253
              ],
              [
                104.31074893972789,
                52.291635044994344
              ],
              [
                104.31440579832234,
                52.2900636734107
              ],
              [
                104.31530702055133,
                52.28764253770582
              ],
              [
                104.3173669570748,
                52.2866161465642
              ],
              [
                104.32354676664512,
                52.28606346451235
              ],
              [
                104.32783830106894,
                52.28785307652459
              ],
              [
                104.33127152860803,
                52.28740568033273
              ],
              [
                104.33530557096641,
                52.288405736139545
              ],
              [
                104.33805215299766,
                52.288353102189014
              ],
              [
                104.34028375089802,
                52.28719513937713
              ],
              [
                104.34272992551963,
                52.28764253770582
              ],
              [
                104.34546669877953,
                52.288671695724716
              ],
              [
                104.3498011485476,
                52.28922434507621
              ],
              [
                104.35486515916767,
                52.288145356567135
              ],
              [
                104.3570323840516,
                52.28818483221995
              ],
              [
                104.35568055070804,
                52.29210590443453
              ],
              [
                104.35544451631473,
                52.29673705716864
              ],
              [
                104.34033549400147,
                52.296680786482895
              ],
              [
                104.34026039214905,
                52.298410767762924
              ],
              [
                104.33667696090512,
                52.29821343492699
              ],
              [
                104.32737575224907,
                52.29786276754704
              ],
              [
                104.32351401713512,
                52.29776254448276
              ],
              [
                104.32312231389007,
                52.29839197959412
              ],
              [
                104.32239138675126,
                52.29859538102315
              ],
              [
                104.32013696489206,
                52.29808838542452
              ],
              [
                104.31899070395944,
                52.299622300166966
              ],
              [
                104.31727718100238,
                52.300939617168325
              ],
              [
                104.31531466496652,
                52.30232226718002
              ],
              [
                104.31362221503119,
                52.30342259004106
              ],
              [
                104.31307013100114,
                52.303745186844054
              ],
              [
                104.31277788297525,
                52.303865297286215
              ],
              [
                104.31244808402322,
                52.30395581127754
              ],
              [
                104.31175629961095,
                52.30411381957547
              ],
              [
                104.31087432144021,
                52.30308789244939
              ],
              [
                104.31017473348253,
                52.30286435269964
              ],
              [
                104.30959695173743,
                52.303250794780126
              ],
              [
                104.30864287302919,
                52.303629814268994
              ],
              [
                104.30776926059137,
                52.30404171503915
              ],
              [
                104.30683742725634,
                52.3043360708223
              ],
              [
                104.30672634987985,
                52.30371294897715
              ],
              [
                104.30327478022731,
                52.30389986680451
              ],
              [
                104.30382605329123,
                52.307726520228435
              ],
              [
                104.3038828014747,
                52.308755469929025
              ],
              [
                104.30417558405153,
                52.3099422204768
              ],
              [
                104.30434202110489,
                52.31114444333
              ],
              [
                104.30456583064759,
                52.311932980273504
              ],
              [
                104.30456433463314,
                52.31214284561783
              ],
              [
                104.30414814232147,
                52.31219550952426
              ],
              [
                104.30361616510785,
                52.31231398849189
              ],
              [
                104.30319684067281,
                52.31252452618845
              ],
              [
                104.30283116041817,
                52.31267588236779
              ],
              [
                104.30231795866763,
                52.31273682351252
              ],
              [
                104.30175111273682,
                52.312745159753355
              ],
              [
                104.30081412196195,
                52.31278966180612
              ],
              [
                104.30003806372795,
                52.31289991969673
              ],
              [
                104.29934658316334,
                52.312933975344315
              ],
              [
                104.29892030765488,
                52.3130528650576
              ]
            ]
          ]
        },
        "properties":{
          "description":"Сумма заказа от 1100 руб.",
          "fill":"#82cdff",
          "fill-opacity":0.6,
          "stroke":"#1e98ff",
          "stroke-width":"5",
          "stroke-opacity":0.9
        }
      },
      {
        "type":"Feature",
        "id":2,
        "geometry":{
          "type":"Polygon",
          "coordinates":[
            [
              [
                104.29439877264508,
                52.23619597384818
              ],
              [
                104.2942784715129,
                52.236594967742334
              ],
              [
                104.2940848956767,
                52.23701399314628
              ],
              [
                104.29378403147999,
                52.23743301457484
              ],
              [
                104.29309821014039,
                52.23801186220604
              ],
              [
                104.2928756176846,
                52.23852614299207
              ],
              [
                104.29208704823427,
                52.24005752007641
              ],
              [
                104.28925463551455,
                52.240511983056074
              ],
              [
                104.2866904436963,
                52.24171068905593
              ],
              [
                104.28387948864874,
                52.243653577461835
              ],
              [
                104.2842485708643,
                52.247526738890656
              ],
              [
                104.28445241874951,
                52.249587902100984
              ],
              [
                104.28409546633375,
                52.250810344278214
              ],
              [
                104.28283557097004,
                52.25117973383041
              ],
              [
                104.28139790693805,
                52.25141678580532
              ],
              [
                104.27796823697614,
                52.250636617276534
              ],
              [
                104.27481751675181,
                52.254847576818285
              ],
              [
                104.27389483685066,
                52.259640648745844
              ],
              [
                104.27256982559727,
                52.26375187322736
              ],
              [
                104.27083711857368,
                52.266190777319466
              ],
              [
                104.2677747329584,
                52.27056406876297
              ],
              [
                104.26614168408541,
                52.27267788438877
              ],
              [
                104.26320424879695,
                52.27588192543097
              ],
              [
                104.26216355169912,
                52.279264485720965
              ],
              [
                104.2608009895195,
                52.28755526745424
              ],
              [
                104.26081932938169,
                52.28928782625912
              ],
              [
                104.26088058458808,
                52.29091505524704
              ],
              [
                104.26538046011316,
                52.29301152298744
              ],
              [
                104.26949128830061,
                52.29495138730223
              ],
              [
                104.27126157546397,
                52.296746450580756
              ],
              [
                104.27170148695596,
                52.29812046420454
              ],
              [
                104.26816901768332,
                52.2979979526985
              ],
              [
                104.26489404047614,
                52.297612327011876
              ],
              [
                104.25968787277819,
                52.29654258862499
              ],
              [
                104.25431004370338,
                52.296314823909505
              ],
              [
                104.24893489683758,
                52.29590369328318
              ],
              [
                104.24566260183938,
                52.29560438777409
              ],
              [
                104.24191823805462,
                52.29483144656307
              ],
              [
                104.24011579359659,
                52.29396968335721
              ],
              [
                104.23917165602337,
                52.29200269505388
              ],
              [
                104.23659673536903,
                52.28788423456769
              ],
              [
                104.2349200114392,
                52.281704897782355
              ],
              [
                104.23397050944787,
                52.279783014554646
              ],
              [
                104.23370765296443,
                52.27786104755593
              ],
              [
                104.23507021514399,
                52.27301648001886
              ],
              [
                104.23781679717524,
                52.27205062894513
              ],
              [
                104.23940466491202,
                52.270589471619566
              ],
              [
                104.24161480514032,
                52.269865456812305
              ],
              [
                104.24352453795893,
                52.26829891137371
              ],
              [
                104.23641399589418,
                52.26515372791169
              ],
              [
                104.23517298545515,
                52.26464543755907
              ],
              [
                104.23436112845853,
                52.263873826102284
              ],
              [
                104.23370843673085,
                52.26296795853269
              ],
              [
                104.23229399764297,
                52.26173949579734
              ],
              [
                104.23034733751345,
                52.261087638111164
              ],
              [
                104.2293697866873,
                52.26040231549919
              ],
              [
                104.22749162700454,
                52.25873306106698
              ],
              [
                104.22751247130432,
                52.257906476807314
              ],
              [
                104.22441781102874,
                52.25437768213409
              ],
              [
                104.22364942062575,
                52.25441228210208
              ],
              [
                104.22256989397711,
                52.25426252105247
              ],
              [
                104.22238494651485,
                52.25379180322875
              ],
              [
                104.22318622573415,
                52.251651852015584
              ],
              [
                104.22519986342819,
                52.252060135351456
              ],
              [
                104.22554106916895,
                52.24977777058443
              ],
              [
                104.22720192174498,
                52.24968815302012
              ],
              [
                104.22704178192635,
                52.25293692154379
              ],
              [
                104.227784887167,
                52.25279788817228
              ],
              [
                104.23017486874286,
                52.251855529012545
              ],
              [
                104.23244428425663,
                52.25102433377756
              ],
              [
                104.23343294406381,
                52.25148541717834
              ],
              [
                104.23742621134198,
                52.24917781123611
              ],
              [
                104.23842740037016,
                52.24923049195451
              ],
              [
                104.23929984336569,
                52.24949389459386
              ],
              [
                104.24006329436318,
                52.250570536527974
              ],
              [
                104.24114861044258,
                52.25119938862901
              ],
              [
                104.24217674831392,
                52.25093105754667
              ],
              [
                104.24311905549683,
                52.25021495127393
              ],
              [
                104.2447890931415,
                52.248927576988805
              ],
              [
                104.24556059717783,
                52.24870120871626
              ],
              [
                104.24594634919598,
                52.24862753521538
              ],
              [
                104.24633210121418,
                52.2486328837593
              ],
              [
                104.2476983427988,
                52.24888116605505
              ],
              [
                104.24897875369498,
                52.249366509940934
              ],
              [
                104.25227618577031,
                52.249364556328906
              ],
              [
                104.25565944853423,
                52.248598728470064
              ],
              [
                104.26279905886446,
                52.24705227635912
              ],
              [
                104.26494997546068,
                52.24238095144853
              ],
              [
                104.26660736559816,
                52.23853906179136
              ],
              [
                104.26633871462921,
                52.23554456311154
              ],
              [
                104.26622424778557,
                52.23407066122461
              ],
              [
                104.26800380821899,
                52.23041289303954
              ],
              [
                104.26873832036748,
                52.22865553016117
              ],
              [
                104.27129695615042,
                52.2274605836655
              ],
              [
                104.27431475269499,
                52.227744304779144
              ],
              [
                104.2772574473872,
                52.227046364198046
              ],
              [
                104.2782957736788,
                52.227550797219344
              ],
              [
                104.2780639183004,
                52.229094295900666
              ],
              [
                104.28044780941309,
                52.22956297717511
              ],
              [
                104.28287461587013,
                52.229860366464145
              ],
              [
                104.28693658627797,
                52.230763101637486
              ],
              [
                104.28881522356937,
                52.23078115931047
              ],
              [
                104.29116592964746,
                52.231326240616035
              ],
              [
                104.29247593862776,
                52.231943779559174
              ],
              [
                104.29305584126548,
                52.232364535157735
              ],
              [
                104.293592828559,
                52.23314101239955
              ],
              [
                104.29318949671287,
                52.23385880696788
              ],
              [
                104.29294073249568,
                52.23542610419874
              ],
              [
                104.29456198912159,
                52.23544127209018
              ],
              [
                104.29439877264508,
                52.23619597384818
              ]
            ]
          ]
        },
        "properties":{
          "description":"Сумма заказа от 1100 руб.",
          "fill":"#82cdff",
          "fill-opacity":0.6,
          "stroke":"#1e98ff",
          "stroke-width":"5",
          "stroke-opacity":0.9
        }
      },
      {
        "type":"Feature",
        "id":3,
        "geometry":{
          "type":"Polygon",
          "coordinates":[
            [
              [
                104.35917755677528,
                52.27560755345279
              ],
              [
                104.36077307422478,
                52.27567632924692
              ],
              [
                104.36136698506438,
                52.2757238793709
              ],
              [
                104.36178923452708,
                52.275652969026424
              ],
              [
                104.36278085803383,
                52.275303514601866
              ],
              [
                104.36327666978721,
                52.275201179727055
              ],
              [
                104.36377248154058,
                52.27517781925502
              ],
              [
                104.36650031639122,
                52.27529959935592
              ],
              [
                104.36632464584206,
                52.276924062850554
              ],
              [
                104.36628308574363,
                52.278538595438945
              ],
              [
                104.36501096274168,
                52.27867086644006
              ],
              [
                104.36511749517346,
                52.27958293990578
              ],
              [
                104.36484292970614,
                52.281181431051614
              ],
              [
                104.36497606000908,
                52.28182574238879
              ],
              [
                104.3675547877139,
                52.28190761409862
              ],
              [
                104.36884415156628,
                52.28194854989655
              ],
              [
                104.36998331171398,
                52.28206844795665
              ],
              [
                104.36998711876456,
                52.282258891945254
              ],
              [
                104.3699050951267,
                52.282475655619635
              ],
              [
                104.36979919139755,
                52.28331561771676
              ],
              [
                104.36982572612665,
                52.283501657045086
              ],
              [
                104.36867041415306,
                52.28365007416463
              ],
              [
                104.36789401376232,
                52.28432369409853
              ],
              [
                104.36745701193112,
                52.2857483543309
              ],
              [
                104.36603832160037,
                52.28669684713273
              ],
              [
                104.3630746788771,
                52.287434779716705
              ],
              [
                104.36210928186985,
                52.287718276549036
              ],
              [
                104.36058598538756,
                52.287764916116025
              ],
              [
                104.35717461199692,
                52.28787135374322
              ],
              [
                104.35763831151029,
                52.286560547153435
              ],
              [
                104.35771444294515,
                52.285175822123165
              ],
              [
                104.35767799187005,
                52.28231436427328
              ],
              [
                104.35725103812983,
                52.281631728060084
              ],
              [
                104.35712669150149,
                52.28120290735884
              ],
              [
                104.3572437436845,
                52.28079020924926
              ],
              [
                104.35746808422805,
                52.27939701110004
              ],
              [
                104.35630188971781,
                52.279145346044956
              ],
              [
                104.3566302520399,
                52.275502907382496
              ],
              [
                104.35917755677528,
                52.27560755345279
              ]
            ]
          ]
        },
        "properties":{
          "description":"Сумма заказа от 1100 руб.",
          "fill":"#82cdff",
          "fill-opacity":0.6,
          "stroke":"#1e98ff",
          "stroke-width":"5",
          "stroke-opacity":0.9
        }
      },
      {
        "type":"Feature",
        "id":4,
        "geometry":{
          "type":"Point",
          "coordinates":[
            104.29042273754133,
            52.27333480057664
          ]
        },
        "properties":{
          "description":"Наш ресторан",
          "iconCaption":"Фо Ми",
          "marker-color":"#f371d1"
        }
      }
    ]
}